bedrock_swarm/__init__.py
bedrock_swarm/events.py
bedrock_swarm/exceptions.py
bedrock_swarm/logging.py
bedrock_swarm/py.typed
bedrock_swarm/types.py
bedrock_swarm/agency/__init__.py
bedrock_swarm/agency/agency.py
bedrock_swarm/agency/thread.py
bedrock_swarm/agents/__init__.py
bedrock_swarm/agents/base.py
bedrock_swarm/config/__init__.py
bedrock_swarm/memory/__init__.py
bedrock_swarm/memory/base.py
bedrock_swarm/models/__init__.py
bedrock_swarm/models/base.py
bedrock_swarm/models/claude.py
bedrock_swarm/models/factory.py
bedrock_swarm/models/titan.py
bedrock_swarm/tools/__init__.py
bedrock_swarm/tools/base.py
bedrock_swarm/tools/calculator.py
bedrock_swarm/tools/factory.py
bedrock_swarm/tools/send_message.py
bedrock_swarm/tools/time.py
bedrock_swarm/tools/validation.py
bedrock_swarm-0.4.0.dist-info/LICENSE
bedrock_swarm-0.4.0.dist-info/METADATA
bedrock_swarm-0.4.0.dist-info/WHEEL
bedrock_swarm-0.4.0.dist-info/top_level.txt
bedrock_swarm-0.4.0.dist-info/RECORD
