Metadata-Version: 2.2
Name: bedrock-swarm
Version: 0.4.0
Summary: A framework for building multi-agent systems using AWS Bedrock
Author-email: Chris Sandrini <mail@chrissandrini.ch>
License: MIT License
Classifier: Development Status :: 3 - Alpha
Classifier: Intended Audience :: Developers
Classifier: License :: OSI Approved :: MIT License
Classifier: Programming Language :: Python :: 3
Classifier: Programming Language :: Python :: 3.9
Classifier: Programming Language :: Python :: 3.10
Classifier: Programming Language :: Python :: 3.11
Requires-Python: >=3.9
License-File: LICENSE
Requires-Dist: boto3>=1.28.0
Requires-Dist: pydantic>=2.0.0
Requires-Dist: rich>=13.0.0
Requires-Dist: typing-extensions>=4.7.0
Requires-Dist: python-dotenv>=1.0.0
Requires-Dist: jsonschema>=4.17.0
Requires-Dist: tzdata>=2024.1
Provides-Extra: dev
Requires-Dist: pytest>=7.0.0; extra == "dev"
Requires-Dist: pytest-cov>=4.0.0; extra == "dev"
Requires-Dist: black>=23.0.0; extra == "dev"
Requires-Dist: isort>=5.12.0; extra == "dev"
Requires-Dist: flake8>=6.0.0; extra == "dev"
Requires-Dist: pre-commit>=3.0.0; extra == "dev"
Provides-Extra: docs
Requires-Dist: mkdocs>=1.4.0; extra == "docs"
Requires-Dist: mkdocs-material>=9.0.0; extra == "docs"
Requires-Dist: mkdocstrings>=0.22.0; extra == "docs"
Requires-Dist: mkdocstrings-python>=1.1.0; extra == "docs"
Requires-Dist: mkdocs-mermaid2-plugin>=1.1.0; extra == "docs"
